viddiffusion/__init__.py
viddiffusion/image_utils.py
viddiffusion/pipeline_viddiffusion.py
viddiffusion/video_utils.py
viddiffusion-0.1.2.dist-info/LICENSE
viddiffusion-0.1.2.dist-info/METADATA
viddiffusion-0.1.2.dist-info/WHEEL
viddiffusion-0.1.2.dist-info/top_level.txt
viddiffusion-0.1.2.dist-info/RECORD
