Metadata-Version: 2.1
Name: viddiffusion
Version: 0.1.2
Summary: VidDiffusion is a Python library that provides vid2vid pipeline by using Hugging Face's `diffusers`.
Home-page: https://github.com/masaishi/VidDiffusion
Author: Masamune Ishihara
Author-email: masaishi_masa@yahoo.co.jp
Maintainer: Masamune Ishihara
Maintainer-email: masaishi_masa@yahoo.co.jp
License: Apache License 2.0
Platform: UNKNOWN
Requires-Python: >=3.6
License-File: LICENSE
Requires-Dist: opencv-python
Requires-Dist: tqdm
Requires-Dist: Pillow
Requires-Dist: torch
Requires-Dist: transformers
Requires-Dist: diffusers
Requires-Dist: accelerate
